kervi
