Metadata-Version: 1.0
Name: kervi-hal-rpi
Version: 0.20.22
Summary: Raspberry pi hardware abstraction layer for the Kervi automation framework
Home-page: https://kervi.org
Author: Tim Wentzlau
Author-email: tim.wentzlau@gmail.com
License: UNKNOWN
Platform: UNKNOWN
